<?xml version="1.0" encoding="UTF-8"?>
<databaseChangeLog
		xmlns="http://www.liquibase.org/xml/ns/dbchangelog"
		xmlns:xsi="http://www.w3.org/2001/XMLSchema-instance"
		xsi:schemaLocation="http://www.liquibase.org/xml/ns/dbchangelog
         http://www.liquibase.org/xml/ns/dbchangelog/dbchangelog-3.0.xsd">


	<changeSet id="201407290939" author="arne" runAlways="true" dbms="oracle">
		<sql>
			ALTER session SET nls_length_semantics=CHAR;
		</sql>
	</changeSet>

	<changeSet id="201407290940B" author="arne">
		<preConditions onFail="MARK_RAN">
			<not>
				<tableExists tableName="across_property_tracking"/>
			</not>
		</preConditions>
		<createTable tableName="across_property_tracking">
			<column name="uuid" type="java.sql.Types.CHAR(36)">
				<constraints nullable="false" primaryKey="true"/>
			</column>
			<column name="hash_code" type="java.sql.Types.CHAR(32)">
				<constraints nullable="false"/>
			</column>
			<column name="module" type="java.sql.Types.VARCHAR(255)"/>
			<column name="properties_id" type="java.sql.Types.VARCHAR(250)"/>
			<column name="database_table" type="java.sql.types.VARCHAR(255)"/>
			<column name="property_name" type="java.sql.Types.VARCHAR(250)"/>
			<column name="first_registration" type="java.sql.Types.TIMESTAMP"/>
			<column name="last_registration" type="java.sql.Types.TIMESTAMP"/>
		</createTable>
		<createIndex tableName="across_property_tracking" indexName="across_pt_hash">
			<column name="hash_code"/>
		</createIndex>
	</changeSet>

</databaseChangeLog>